hcalendar/__init__.py
hcalendar/hcalendar.py
hcalendar/vcalendar.py
hcalendar/vevent.py
hcalendar/vobject.py
python_hcalendar-0.2.4.dist-info/COPYING
python_hcalendar-0.2.4.dist-info/METADATA
python_hcalendar-0.2.4.dist-info/WHEEL
python_hcalendar-0.2.4.dist-info/top_level.txt
python_hcalendar-0.2.4.dist-info/RECORD
