Metadata-Version: 2.1
Name: python-hcalendar
Version: 0.2.4
Summary: python-hcalendar is a basic hCalendar parser
Home-page: https://github.com/mback2k/python-hcalendar
Author: Marc Hoersken
Author-email: info@marc-hoersken.de
License: MIT
Platform: UNKNOWN
Classifier: Intended Audience :: Developers
Classifier: License :: OSI Approved :: MIT License
Classifier: Programming Language :: Python
Classifier: Topic :: Text Processing :: Markup :: HTML
Classifier: Topic :: Software Development :: Libraries :: Python Modules
Classifier: Development Status :: 4 - Beta
Classifier: Operating System :: OS Independent
Requires-Dist: beautifulsoup4 (>=4.3.2)
Requires-Dist: isodate (>=0.5.0)
